AUTHORS
LICENSE
MANIFEST.in
README.rst
setup.py
gwebsocket/__init__.py
gwebsocket/exceptions.py
gwebsocket/handler.py
gwebsocket/logging.py
gwebsocket/resource.py
gwebsocket/server.py
gwebsocket/utf8validator.py
gwebsocket/websocket.py
gwebsocket.egg-info/PKG-INFO
gwebsocket.egg-info/SOURCES.txt
gwebsocket.egg-info/dependency_links.txt
gwebsocket.egg-info/not-zip-safe
gwebsocket.egg-info/requires.txt
gwebsocket.egg-info/top_level.txt
gwebsocket/gunicorn/__init__.py
gwebsocket/gunicorn/workers.py
gwebsocket/protocols/__init__.py
gwebsocket/protocols/base.py