Metadata-Version: 1.1
Name: gwebsocket
Version: 0.9.9
Summary: Websocket handler for the gevent pywsgi server, a Python network library
Home-page: https://bitbucket.org/btubbs/gwebsocket
Author: Brent Tubbs
Author-email: brent.tubbs@gmail.com
License:    Copyright 2011-2013 Jeffrey Gelens <jeffrey@noppo.pro>
